readmedocs_fetcher_haystack/__about__.py
readmedocs_fetcher_haystack/__init__.py
readmedocs_fetcher_haystack/readmedocs_fetcher.py
readmedocs_fetcher_haystack-0.0.2.dist-info/METADATA
readmedocs_fetcher_haystack-0.0.2.dist-info/WHEEL
readmedocs_fetcher_haystack-0.0.2.dist-info/licenses/LICENSE.txt
readmedocs_fetcher_haystack-0.0.2.dist-info/RECORD
